supabase_mcp/__init__.py
supabase_mcp/client.py
supabase_mcp/exceptions.py
supabase_mcp/logger.py
supabase_mcp/main.py
supabase_mcp/queries.py
supabase_mcp/settings.py
supabase_mcp/validators.py
supabase_mcp_server_kivo-0.4.0.dist-info/METADATA
supabase_mcp_server_kivo-0.4.0.dist-info/WHEEL
supabase_mcp_server_kivo-0.4.0.dist-info/entry_points.txt
supabase_mcp_server_kivo-0.4.0.dist-info/licenses/LICENSE
supabase_mcp_server_kivo-0.4.0.dist-info/RECORD
