Metadata-Version: 2.4
Name: supabase-mcp-server-kivo
Version: 0.4.0
Summary: Unofficial MCP server for Supabase providing basic schema, table, and column management.
Project-URL: Homepage, https://github.com/alexander-zuev/supabase-mcp-server
Project-URL: Repository, https://github.com/alexander-zuev/supabase-mcp-server.git
Project-URL: Changelog, https://github.com/alexander-zuev/supabase-mcp-server/blob/main/CHANGELOG.MD
Project-URL: Documentation, https://github.com/alexander-zuev/supabase-mcp-server#readme
Author-email: Kevin Hill <kevin@geodexes.com>
License-Expression: Apache-2.0
License-File: LICENSE
Keywords: cursor,mcp,supabase,windsurf
Classifier: Development Status :: 4 - Beta
Classifier: Intended Audience :: Developers
Classifier: License :: OSI Approved :: Apache Software License
Classifier: Programming Language :: Python :: 3.12
Classifier: Topic :: Database :: Database Engines/Servers
Classifier: Topic :: Software Development :: Libraries :: Python Modules
Requires-Python: >=3.12
Requires-Dist: mcp[cli]>=1.2.1
Requires-Dist: psycopg[binary,pool]
Requires-Dist: supabase>=2.13.0
Requires-Dist: tenacity>=9.0.0
